{
  "cameras": {
    "Canon Canon EOS REBEL T5i": 22428,
    "SONY ILCE-7M4": 2767,
    "Canon Canon EOS R6": 2488,
    "SONY ILCE-7M3": 1852,
    "Canon Canon EOS R6m2": 1646,
    "Canon Canon EOS R": 1351,
    "NIKON CORPORATION NIKON D850": 969,
    "Canon Canon EOS 6D Mark II": 933,
    "Hasselblad L2D-20c": 910,
    "DJI FC3411": 858,
    "Canon Canon EOS R5": 843,
    "Canon Canon EOS 90D": 790,
    "DJI FC8482": 740,
    "NIKON CORPORATION NIKON Z 6": 708,
    "Apple iPhone 16 Pro Max": 690,
    "DJI FC8282": 679,
    "Apple iPhone 15 Pro Max": 614,
    "Apple iPhone 14 Pro Max": 596,
    "SONY ILCE-7RM2": 534,
    "anon Canon EOS REBEL T5i": 515,
    "Canon Canon EOS 5D Mark IV": 508,
    "Apple iPhone 16 Pro": 481,
    "Canon Canon EOS RP": 480,
    "NIKON CORPORATION NIKON D750": 472,
    "NIKON CORPORATION NIKON Z6_3": 467,
    "NIKON CORPORATION NIKON Z 7_2": 464,
    "Apple iPhone 13 Pro Max": 452,
    "SONY ILCE-7SM3": 414,
    "Apple iPhone 15 Pro": 413,
    "Apple iPhone 14 Pro": 409,
    "NIKON CORPORATION NIKON D7500": 405,
    "DJI FC3582": 399,
    "samsung Galaxy S24 Ultra": 387,
    "NIKON CORPORATION NIKON Z 6_2": 367,
    "Canon Canon EOS R8": 366,
    "DJI FC9113": 363,
    "NIKON CORPORATION NIKON D810": 362,
    "Apple iPhone 13 Pro": 344,
    "Apple iPhone 13": 336,
    "Canon Canon EOS 5D Mark III": 336,
    "SONY ILCE-7RM4": 321,
    "DJI FC3170": 316,
    "Hasselblad L1D-20c": 301,
    "samsung Galaxy S23 Ultra": 296,
    "Apple iPhone 15": 290,
    "Apple iPhone 12 Pro Max": 284,
    "Canon Canon EOS Rebel T8i": 263,
    "Apple iPad Pro 11.0 inch 3": 261,
    "Apple iPhone 14": 260,
    "Canon Canon EOS 80D": 249
  },
  "photographers": {
    "Rocket Lister AZ; LLC": 5016,
    "Rocket Lister; LLC": 684,
    "Rocket Lister AZ": 578,
    "JARET MILLER PHOTOGRAPHY": 405,
    "Ali": 347,
    "Kent E Patterson": 323,
    "JOEY AMBROSE": 296,
    "Stephen Miller": 259,
    "DOUG SHELL": 222,
    "@2019 Brian Ogrisek": 215,
    "Ken Lam": 214,
    "Nelson T": 209,
    "Garrett Sidler": 204,
    "Jason Check": 190,
    "TERRY MAG PHOTOGRAPHY": 187,
    "Picasa": 186,
    "Ron Quarles": 177,
    "A O Tucker": 173,
    "Michael Small": 169,
    "Charles W Miller": 166,
    "austinbuchanan": 155,
    "Joshua Mason-Barkin": 148,
    "kurt munger": 146,
    "Aaron Wells": 143,
    "Marlon DeCastro": 142,
    "Matt Wilczek": 142,
    "Stephen Shefrin": 135,
    "AUSTIN BUCHANAN": 131,
    "Joshua Mason-Barkin / List Logix, LLC": 126,
    "Chris Paxman": 124,
    "Cari Hall/MarketExpertly 20254": 120,
    "Mario Alfredo PHOTOGRAPHY": 119,
    "X\nSteve Weiss": 119,
    "nimbusimaging.com": 118,
    "RBMW Ventures LLC": 115,
    "COLTON SIMON": 110,
    "TODD FRENCH": 110,
    "Anthony Giammarino": 108,
    "J. Int Veld": 107,
    "PlanOmatic": 105,
    "Joey Ambrose": 103,
    "Dave Carter/Carter Photography": 101,
    "Eric Jewett": 100,
    "CASEY PICKARD": 96,
    "Christina Lawrie": 94,
    "Thomas Barnett": 93,
    "JAKE_SSHOOTER": 91,
    "Damian": 86,
    "Taylor Morrison": 78,
    "CAMERON HOILAND": 74,
    "Pixelist Media": 73,
    "SHANE BRANDOLINI": 71,
    "Rocket Lister": 70,
    "Snap2Close": 69,
    "Gabriel Eriksson\n480.549.3003\nAll Rights Reserved": 69,
    "VHT Studios - www.VHT.com": 68,
    "Trace Tague": 56,
    "Dave Sheble": 55,
    "BoomPix LLC": 54,
    "Sunshine Hebert": 52,
    "JOHN BUTTEL": 49,
    "HOWARD PALEY": 49,
    "JANAE STROUD": 43,
    "TMRiddle": 41,
    "Tygo Studio": 41,
    "DANIEL HAYNES": 40,
    "Jack Jackson": 40,
    "SaguaroPictures.com": 40,
    "ChapterNEXT Photography": 39,
    "cragrootimaging.com": 38,
    "Christy + Frank @ Willo Art/Simonphotographic": 35,
    "Isaac Murray": 33,
    "Heather Kadar": 33,
    "Johnson, Debra": 33,
    "Jim Barker": 32,
    "2": 32,
    "KEVIN KAPLAN": 31,
    "Shelley Christine": 31,
    "Rocket Lister AZ;LLC": 29,
    "THE LISTING BEES": 29,
    "Reelist Productions": 27,
    "\u0002": 27,
    "Daniel J. CORDERO": 26,
    "Kevin Brost LLC": 26,
    "Jonathan Lui": 26,
    "Christy Pickrell@Willo Art": 26,
    "RYAN WILSON": 25,
    "Daniel Parrotta": 24,
    "Cari Hall/MarketExpertly 2024": 24,
    "VALENTINO PEREZ": 24,
    "Brian Serwa": 24,
    "HEATHER": 23,
    "Ina Ivanova Photography": 23,
    "craigrootimaging": 21,
    "G REID HELMS": 21,
    "Emilio Ferrara": 20,
    "Kirk Krein": 20,
    "DAN WARFIED": 20,
    "Photographer:Joe Ercoli": 20,
    "Aerial 360 - Robb Bucklin": 20
  },
  "preferred_photographers": {
    "Rocket Lister": 21446,
    "Mobile Device": 11479,
    "ListerPros": 4192,
    "Boompix": 1617,
    "Competitor 2": 1179,
    "Haus Photo Co.": 995,
    "Competitor 13": 928,
    "Lister Assister": 849,
    "Competitor 11": 594,
    "New Build Render": 583,
    "KC Creative Design": 547,
    "Pixelist Media": 481,
    "Red Hog Media": 435,
    "Kent E Patterson": 433,
    "Premier Lister": 412,
    "Desert Paradise Productions": 387,
    "Jaret MIller": 365,
    "Exposure Media": 336,
    "Nelson": 330,
    "Competitor 5": 289,
    "Luxe": 279,
    "M.Clay Photography": 273,
    "Mario Alfredo Photography": 271,
    "Ron Quarles": 269,
    "Competitor 14": 260,
    "Showingtime Plus": 224,
    "Competitor 10": 215,
    "Competitor 16": 211,
    "List Logix": 206,
    "Arizona Listing Media": 205,
    "Ali": 204,
    "Stephen Shefrin": 180,
    "Competitor 8": 174,
    "CARLOS CHAVEZ": 165,
    "Anthony Giammarino": 161,
    "Michael Small": 160,
    "Competitor 3": 151,
    "Picasa": 148,
    "Colton Simon": 147,
    "Marlon DeCastro": 146,
    "Competitor 9": 137,
    "Competitor 12": 134,
    "Hub Media": 134,
    "Dave Carter": 130,
    "Competitor 1": 123,
    "Matt Wilczek": 121,
    "Casey Pickard": 118,
    "Birds Eye Vue": 111,
    "Brave Fox Photo": 106,
    "Paxman Photography": 105,
    "Aaron Wells": 101,
    "John Buttel": 98,
    "Tigrphoto": 94,
    "Todd French": 93,
    "Bryan Blair": 92,
    "PlanOmatic": 91,
    "Trace Tague": 86,
    "Craig Root Imaging": 83,
    "Howard Paley": 83,
    "Chase Capture": 82,
    "Mile High Photos": 81,
    "Thomas Barnett": 79,
    "Showtime Plus": 79,
    "jairo": 78,
    "Your Online Guy": 68,
    "ChapterNEXT Photography": 65,
    "Applied Photography": 65,
    "Jim Doyle": 64,
    "Daniel Haynes": 59,
    "Market Expertly": 51,
    "Shane Brandolini": 51,
    "Audra White": 50,
    "David Bruce Norton": 49,
    "VeldPhoto": 48,
    "Off Kilter": 48,
    "Chris Paxman": 46,
    "Desert Star Photography": 46,
    "ROBERTO HEREDIA": 43,
    "FRANK DATZER": 42,
    "Cole Horchler": 40,
    "Willo Art": 40,
    "Kevin Brost": 38,
    "Damian": 38,
    "Legoullon": 37,
    "Timber Creek Imagery": 33,
    "Daniel Cordero": 32,
    "Josh Wallace": 32,
    "David Peterson Photography": 31,
    "Applegate": 30,
    "Alex Garcia": 29,
    "Shelley Christine": 29,
    "Matthew Echavarria REC MEDIA": 28,
    "Jim Barker": 26,
    "Kirk Krein": 25,
    "Jack Jackson": 25,
    "Hunter Lomayesva": 25,
    "Karlie Colleen Photography": 25,
    "Planomatic": 24,
    "CHETHESHOOTER": 24,
    "Tyler Kinzer": 24,
    "Leslie Morgan": 21,
    "Lady Fame": 21,
    "Ina Ivanova Photography": 20,
    "Daniel Parrotta": 20,
    "Jaret Miller": 20,
    "Jennifer Rice": 19,
    "Randall Dubs": 19,
    "EMA Photography": 19,
    "Eric Kruk": 18,
    "GreenLightPhotography": 18,
    "Dustin Rosbery": 18,
    "Stephen Shawl": 16,
    "Pavlik Productions LLC": 15,
    "Robert Morales": 15,
    "Danielle Levian": 15,
    "Harold Rush": 14,
    "Andrew Pielage": 14,
    "Reid Helms": 14,
    "Patrick Caughlan": 14,
    "Competitor 6": 13,
    "Volo Photo": 13,
    "Gabriel Eriksson": 13,
    "KIM LABRIOLA": 13,
    "Bryan Blair Prod.": 12,
    "DAVID B NORTON": 12,
    "Beau MacDonnell": 12,
    "Christal Stratton": 11,
    "Christina Moca": 11,
    "Lauren Grace Bailey": 11,
    "Charlotte Nelson": 11,
    "Team Woodall": 11,
    "AHO": 10,
    "Alex Jacob Reyes": 10,
    "Nichole Hancock Photography": 10,
    "Mykol Lagarde": 10,
    "JOHN BAE": 10,
    "Ray Cleveland": 10,
    "Through the hoop": 10,
    "SAMANTHA MACKEY": 10,
    "Sky Makai": 9,
    "Jason Youn": 9,
    "DeWitt Lang": 9,
    "James Pierre": 9,
    "EliteMedia.pro": 9,
    "Jason Jones Photography": 9,
    "Fullview 360": 9,
    "Ryan Wilson": 9,
    "Donatas Zadeikis": 9,
    "DRW": 9,
    "Laurelle": 8,
    "JR Cameraworks": 8,
    "Chantil Marie": 8,
    "Darren Anderson": 8,
    "Christian Blok": 8,
    "Competitor 7": 8,
    "Lisa O'Donnell": 8,
    "Kirsten Smith": 8,
    "Coleman A": 7,
    "Damon Overson": 7,
    "Jonathan Arlia": 7,
    "Steve Weiss": 7,
    "Simon Photographic": 7,
    "Thea Tammer": 7,
    "Samantha Nieto Photography": 6,
    "Heidi Halverson Photography": 6,
    "Carlos Chavez": 6,
    "Paolo Cascio": 6,
    "Bryan Bouchard": 6,
    "David Swanson": 6,
    "CJ Gershon Photography": 6,
    "Hector Meraz": 6,
    "Andrew McQuality": 5,
    "Steve Njavro": 5,
    "Adam Weklak": 5,
    "Alex Rentzis": 5,
    "Heather Kadar": 5,
    "Jaeger Amzallag": 5,
    "Michael Woodall": 5,
    "Shane Baker Studios": 5,
    "Paula Scott": 5,
    "Clayton Hinkle": 5,
    "Ryan Guzzetta": 5,
    "Jenn Hanks": 5,
    "Brilliant Exposures": 5,
    "Swifro": 5,
    "munoz": 5,
    "LJ Garcia Studios": 4,
    "Juan Avalos": 4,
    "Christina Lawrie": 4,
    "Sherri Graves Photography": 4,
    "Kimberly Martinez": 4,
    "NKL Photography, LLC": 4,
    "Ron": 4,
    "Ana Maga": 4,
    "Emilio Ferrara": 4,
    "Greg Schuster": 4,
    "Karen Bock Photography": 4,
    "Michael Falconer": 4,
    "LuAnn Prillaman": 4,
    "YVETTE M PALMER": 4,
    "Daniel Radfrod": 4,
    "Ali Megan": 4,
    "ANITA MCLEOD": 4,
    "Mitchell Lindell": 3,
    "Nick Nelson": 3,
    "Albina": 3,
    "Kristen Cluff": 3,
    "YILIUBAI PHOTOGRAPHY": 3,
    "VHT Studios": 3,
    "Brightr Media": 3,
    "Lomeli": 3,
    "Jake Shooter": 3,
    "Elizabeth Wells Photography": 3,
    "Mark Boisclair": 3,
    "Tam Truong": 3,
    "Jason Roehner": 3,
    "Mike Lanouar": 3,
    "Tyler Davis": 3,
    "Marine Kooistra": 3,
    "Wayne Xu Photography": 3,
    "GERARDO GARCIA": 3,
    "Giuseppe DeMasi": 3,
    "Erik Espinoza": 2,
    "Greg Barber": 2,
    "Catherine Foland": 2,
    "Sue Wright": 2,
    "Joseph Martori II": 2,
    "Casey Galloway": 2,
    "Andrew Lakotko": 2,
    "Jess": 2,
    "Natasha Mishano": 2,
    "Pablo Robles": 2,
    "Brian Wilmington": 2,
    "Rylan Dressendorfer": 2,
    "Hi Res Media": 2,
    "Phoenix Drone Pros": 2,
    "HAZ Vacation Rentals": 2,
    "Snap2Close": 2,
    "Kay Ceili O'Bryan": 2,
    "Scott Galles": 2,
    "Chuck Taylor": 2,
    "Kelli Johnson": 2,
    "Bryan C. Nelson": 2,
    "Tyler Flack": 2,
    "Nemec Photography": 2,
    "Connor Hutchings": 2,
    "KK Photography": 2,
    "Nathan Camasura": 2,
    "Dallas M Rogers": 2,
    "Matthew Hoffman": 2,
    "FCE": 2,
    "Karin Munson": 2,
    "Eirini Pajak": 1,
    "Brad Snyder": 1,
    "Leslie Styler Phography": 1,
    "Lynn Chyi": 1,
    "Allen Dimitri": 1,
    "Doug Shell": 1,
    "Anthony Snaps": 1,
    "Jeffrey Starr": 1,
    "Marco Leone": 1,
    "Andrew Shields": 1,
    "Paul Duro": 1,
    "Roberto Heredia": 1,
    "Clayton Homes": 1,
    "Mark Longhi": 1,
    "Property Image Co.": 1,
    "Donald Neuerman": 1,
    "Melody Van Hammond": 1,
    "eli grimmett": 1,
    "John Ott": 1,
    "Dominique Ramirez": 1,
    "Eric Jewett": 1,
    "Joel Messina": 1,
    "Chau Tran": 1,
    "Dooley Images": 1,
    "Jessica Peterson": 1,
    "Bre Redmond": 1,
    "Peter Kertz": 1,
    "Josh Ercanbrack": 1,
    "Nicholas Flournoy": 1,
    "Eric Stahl": 1,
    "Joe Cross": 1,
    "Jason Rasch": 1,
    "Angelie Allegado": 1,
    "Tommie Cochrun": 1,
    "Len Catalanotto": 1,
    "Greg Utton": 1,
    "Brian Karow": 1,
    "Ryan": 1,
    "Guess": 1,
    "Jara Minter": 1,
    "Erica Shurter": 1,
    "Tom Brownold": 1,
    "Kristy Velesko": 1,
    "Brandon Dodd": 1,
    "BearDog Productions": 1,
    "Kaylee Chelsea Photography": 1,
    "Manager Scottsdale GI Consultants": 1,
    "ENZO PHOTO CO. 2023": 1,
    "ROBERT DEAN IMAGERY": 1,
    "Scott Blake": 1,
    "NICHOLAS THIBAULT": 1,
    "Nick Robbs Photography": 1,
    "Bridget Clarice": 1
  },
  "updated": "2025-12-24T02:10:16.919420+00:00"
}